bettertest/__init__.py
bettertest/promptTemplate.py
bettertest/test.py
bettertest-0.1.98.dist-info/METADATA
bettertest-0.1.98.dist-info/WHEEL
bettertest-0.1.98.dist-info/RECORD
