Metadata-Version: 2.1
Name: bettertest
Version: 0.1.98
Summary: 
Author: krrishdholakia
Author-email: krrishdholakia@gmail.com
Requires-Python: >=3.8,<4.0
Classifier: Programming Language :: Python :: 3
Classifier: Programming Language :: Python :: 3.8
Classifier: Programming Language :: Python :: 3.9
Classifier: Programming Language :: Python :: 3.10
Classifier: Programming Language :: Python :: 3.11
Requires-Dist: openai (>=0.27.2,<0.28.0)
Requires-Dist: supabase (>=1.0.3,<2.0.0)
Requires-Dist: tenacity (>=8.2.2,<9.0.0)
